classyjson.py
tests/__init__.py
tests/test_classy.py
tests/test_dotdict.py
tests/test_load.py
tests/test_schema.py
classyjson-0.1.2.dist-info/LICENSE
classyjson-0.1.2.dist-info/METADATA
classyjson-0.1.2.dist-info/WHEEL
classyjson-0.1.2.dist-info/top_level.txt
classyjson-0.1.2.dist-info/RECORD
