Metadata-Version: 2.1
Name: classyjson
Version: 0.1.2
Summary: Wrap jsonschema in python classes
Home-page: https://github.com/earthastronaut/classyjson
Author: Dylan Gregersen
Author-email: an.email0101@gmail.com
License: MIT
Platform: UNKNOWN
Classifier: License :: OSI Approved :: MIT License
Classifier: Programming Language :: Python
Requires-Python: >=3.5
License-File: LICENSE
